xo1/__init__.py
xo1/app.py
xo1/color.py
xo1/render.py
xo1/surface.py
xo1/window.py
xo1-0.2.0.dist-info/LICENSE
xo1-0.2.0.dist-info/WHEEL
xo1-0.2.0.dist-info/METADATA
xo1-0.2.0.dist-info/RECORD
