Metadata-Version: 2.1
Name: xo1
Version: 0.2.0
Summary: EAF-based framework for creating terminal applications
Home-page: https://github.com/pkulev/xo1
License: MIT
Keywords: curses,terminal,application,framework
Author: Pavel Kulyov
Author-email: kulyov.pavel@gmail.com
Requires-Python: >=3.7,<4.0
Classifier: Development Status :: 3 - Alpha
Classifier: Environment :: Console :: Curses
Classifier: Intended Audience :: Developers
Classifier: License :: OSI Approved :: MIT License
Classifier: Operating System :: POSIX :: Linux
Classifier: Programming Language :: Python :: 3
Classifier: Programming Language :: Python :: 3.7
Classifier: Programming Language :: Python :: 3.8
Requires-Dist: eaf (>=0.2,<0.3)
Project-URL: Repository, https://github.com/pkulev/xo1
